{"question": "how do I code in Python?"}
{"question": "how do I code in Java?"}
{"question": "im confused?"}
{"question": "how do I code in Python?"}
{"question": "how do I code in Java?"}
{"question": "im confused?"}
{"question": "im confused.com?"}
{"question": "How do i code?"}
{"question": "what is the weather like tomorrow?"}
{"question": "who created you?"}
{"question": "Whats the weather like today?"}
{"question": "who created you?"}
{"question": "im feeling overwhelmed"}
{"question": "why do i get angry so quickly?"}
{"question": "im okay"}
{"question": "im good"}
{"question": "im fine"}
{"question": "im fine"}
